zgoubi_metadata/__init__.py
zgoubi_metadata/elements.py
zgoubi_metadata/data/elements_yaml/BEND.yaml
zgoubi_metadata/data/elements_yaml/CAVITE.yaml
zgoubi_metadata/data/elements_yaml/CHAMBR.yaml
zgoubi_metadata/data/elements_yaml/CHANGREF.yaml
zgoubi_metadata/data/elements_yaml/DIPOLE.yaml
zgoubi_metadata/data/elements_yaml/DIPOLES.yaml
zgoubi_metadata/data/elements_yaml/DRIFT.yaml
zgoubi_metadata/data/elements_yaml/END.yaml
zgoubi_metadata/data/elements_yaml/FAISCEAU.yaml
zgoubi_metadata/data/elements_yaml/FAISCNL.yaml
zgoubi_metadata/data/elements_yaml/FAISTORE.yaml
zgoubi_metadata/data/elements_yaml/FFAG.yaml
zgoubi_metadata/data/elements_yaml/MARKER.yaml
zgoubi_metadata/data/elements_yaml/MATRIX.yaml
zgoubi_metadata/data/elements_yaml/MCDESINT.yaml
zgoubi_metadata/data/elements_yaml/MULTIPOL.yaml
zgoubi_metadata/data/elements_yaml/ORDRE.yaml
zgoubi_metadata/data/elements_yaml/PARTICUL.yaml
zgoubi_metadata/data/elements_yaml/POLARMES.yaml
zgoubi_metadata/data/elements_yaml/QUADRUPO.yaml
zgoubi_metadata/data/elements_yaml/REBELOTE.yaml
zgoubi_metadata/data/elements_yaml/SCALING.yaml
zgoubi_metadata/data/elements_yaml/SPNPRNL.yaml
zgoubi_metadata/data/elements_yaml/SPNPRT.yaml
zgoubi_metadata/data/elements_yaml/SPNSTORE.yaml
zgoubi_metadata/data/elements_yaml/TOSCA.yaml
zgoubi_metadata/data/elements_yaml/YMY.yaml
Zgoubi_metadata-0.1.dist-info/LICENSE
Zgoubi_metadata-0.1.dist-info/METADATA
Zgoubi_metadata-0.1.dist-info/WHEEL
Zgoubi_metadata-0.1.dist-info/top_level.txt
Zgoubi_metadata-0.1.dist-info/RECORD
