Metadata-Version: 2.1
Name: Zgoubi-metadata
Version: 0.1
Summary: Metadata for building software to interact with Zgoubi
Home-page: https://github.com/PyZgoubi/zgoubi-metadata
Author: Sam Tygier
Author-email: sam@tygier.co.uk
License: UNKNOWN
Platform: UNKNOWN
Classifier: Programming Language :: Python :: 3
Classifier: License :: OSI Approved :: MIT License
Classifier: Operating System :: OS Independent
Requires-Python: >=3.6
Requires-Dist: PyYAML (>=5.3)
